additional_urwid_widgets/__init__.py
additional_urwid_widgets/assisting_modules/__init__.py
additional_urwid_widgets/assisting_modules/modifier_key.py
additional_urwid_widgets/assisting_modules/useful_functions.py
additional_urwid_widgets/widgets/__init__.py
additional_urwid_widgets/widgets/date_picker.py
additional_urwid_widgets/widgets/indicative_listbox.py
additional_urwid_widgets/widgets/integer_picker.py
additional_urwid_widgets/widgets/message_dialog.py
additional_urwid_widgets/widgets/selectable_row.py
additional_urwid_widgets-0.4.1.dist-info/LICENSE
additional_urwid_widgets-0.4.1.dist-info/METADATA
additional_urwid_widgets-0.4.1.dist-info/WHEEL
additional_urwid_widgets-0.4.1.dist-info/top_level.txt
additional_urwid_widgets-0.4.1.dist-info/RECORD
